Metadata-Version: 2.1
Name: pyAlgebra
Version: 0.1
Summary: performs integral and differentiable operations on string expressions using sympy
Home-page: https://github.com/prakHr/pyAlgebra-v
Maintainer: Prakhar Gandhi
Maintainer-email: gprakhar0@gmail.com
License: UNKNOWN
Download-URL: https://github.com/prakHr/pyAlgebra-v/archive/refs/tags/v01.tar.gz
Platform: UNKNOWN
License-File: LICENSE.txt
